frmastro/astro.py
frmastro/const.py
frmastro/datetime
frmastro/filter_tracings/galex_fuv.dat
frmastro/filter_tracings/galex_nuv.dat
frmastro/filter_tracings/irac_1.dat
frmastro/filter_tracings/irac_2.dat
frmastro/filter_tracings/irac_3.dat
frmastro/filter_tracings/irac_4.dat
frmastro/filter_tracings/johnson_b.dat
frmastro/filter_tracings/johnson_i.dat
frmastro/filter_tracings/johnson_r.dat
frmastro/filter_tracings/johnson_u.dat
frmastro/filter_tracings/johnson_v.dat
frmastro/filter_tracings/mips_24.dat
frmastro/filter_tracings/mips_70.dat
frmastro/filter_tracings/miri-F1000W.dat
frmastro/filter_tracings/miri-F1130W.dat
frmastro/filter_tracings/miri-F1280W.dat
frmastro/filter_tracings/miri-F1500W.dat
frmastro/filter_tracings/miri-F1800W.dat
frmastro/filter_tracings/miri-F2100W.dat
frmastro/filter_tracings/miri-F2550W.dat
frmastro/filter_tracings/miri-F560W.dat
frmastro/filter_tracings/miri-F770W.dat
frmastro/filter_tracings/nircam-F410M.dat
frmastro/filter_tracings/nircam-F444W.dat
frmastro/filter_tracings/nircam-F480M.dat
frmastro/filter_tracings/orig/F410M_mean_system_throughput.txt
frmastro/filter_tracings/orig/F444W_mean_system_throughput.txt
frmastro/filter_tracings/orig/F480M_mean_system_throughput.txt
frmastro/filter_tracings/orig/MIPSfiltsumm.txt
frmastro/filter_tracings/orig/galexfuv.txt
frmastro/filter_tracings/orig/galexnuv.txt
frmastro/filter_tracings/orig/hfilter.dat
frmastro/filter_tracings/orig/irac1filter_2004-08-09.dat
frmastro/filter_tracings/orig/irac2filter_2004-08-09.dat
frmastro/filter_tracings/orig/irac3filter_2004-08-09.dat
frmastro/filter_tracings/orig/irac4filter_2004-08-09.dat
frmastro/filter_tracings/orig/irac_tr1_2004-08-09.dat
frmastro/filter_tracings/orig/irac_tr3_2004-08-09.dat
frmastro/filter_tracings/orig/jfilter.dat
frmastro/filter_tracings/orig/johnsoni.dat
frmastro/filter_tracings/orig/jwst/F277W_NRC_and_OTE_ModAB_mean.txt
frmastro/filter_tracings/orig/jwst/F356W_NRC_and_OTE_ModAB_mean.txt
frmastro-0.1.1.dist-info/WHEEL
frmastro-0.1.1.dist-info/METADATA
frmastro-0.1.1.dist-info/RECORD
